old_swedish_dictionary/__init__.py
old_swedish_dictionary/dictionary.py
old_swedish_dictionary/reader.py
old_swedish_dictionary/resources/__init__.py
old_swedish_dictionary/resources/old-swedish-dictionary.json
old_swedish_dictionary-1.0.0.dist-info/LICENSE
old_swedish_dictionary-1.0.0.dist-info/METADATA
old_swedish_dictionary-1.0.0.dist-info/WHEEL
old_swedish_dictionary-1.0.0.dist-info/top_level.txt
old_swedish_dictionary-1.0.0.dist-info/RECORD
