Metadata-Version: 2.1
Name: old-swedish-dictionary
Version: 1.0.0
Summary: Old Swedish Dictionary for Python. From K.F. Söderwall's Medieval Swedish
Home-page: https://github.com/stscoundrel/old-swedish-dictionary-py
Author: stscoundrel
Requires-Python: >=3.9
License-File: LICENSE
